ejtraderRL/__init__.py
ejtraderRL/agent/__init__.py
ejtraderRL/agent/dqn.py
ejtraderRL/agent/qrdqn.py
ejtraderRL/app/__init__.py
ejtraderRL/app/app.py
ejtraderRL/app/dqn.py
ejtraderRL/app/qrdqn.py
ejtraderRL/data/__init__.py
ejtraderRL/data/get_data.py
ejtraderRL/nn/__init__.py
ejtraderRL/nn/build_model.py
ejtraderRL/nn/block/__init__.py
ejtraderRL/nn/block/conv.py
ejtraderRL/nn/block/convnext.py
ejtraderRL/nn/block/efficient.py
ejtraderRL/nn/layers/__init__.py
ejtraderRL/nn/layers/activation.py
ejtraderRL/nn/layers/attention.py
ejtraderRL/nn/layers/core.py
ejtraderRL/nn/layers/depthwiseconv1d.py
ejtraderRL/nn/layers/lambdalayer.py
ejtraderRL/nn/layers/pyconv.py
ejtraderRL/nn/layers/skconv.py
ejtraderRL/nn/layers/transformer.py
ejtraderRL/nn/losses/__init__.py
ejtraderRL/nn/losses/losses.py
ejtraderRL/nn/model/__init__.py
ejtraderRL/nn/model/ej.py
ejtraderRL-1.0.8.dist-info/LICENSE
ejtraderRL-1.0.8.dist-info/METADATA
ejtraderRL-1.0.8.dist-info/WHEEL
ejtraderRL-1.0.8.dist-info/top_level.txt
ejtraderRL-1.0.8.dist-info/RECORD
