Metadata-Version: 2.1
Name: ejtraderRL
Version: 1.0.8
Summary: Reinforcement learning Trading envoriments.
Home-page: https://github.com/ejejtraderRLabs/
Author: traderpedroso
Author-email: info@ejtrader.com
License: Apache-2.0 License
Keywords: ejtraderRL
Platform: UNKNOWN
License-File: LICENSE
Requires-Dist: numpy
Requires-Dist: ta
Requires-Dist: pandas
Requires-Dist: pandas-datareader
Requires-Dist: matplotlib
Requires-Dist: IPython
